zer/__init__.py
zer/zer.py
zer-0.0.6.dist-info/LICENSE
zer-0.0.6.dist-info/METADATA
zer-0.0.6.dist-info/WHEEL
zer-0.0.6.dist-info/top_level.txt
zer-0.0.6.dist-info/RECORD
