Metadata-Version: 2.1
Name: zer
Version: 0.0.6
Summary: Zer is a Python module for code reduction and automation.
Author: ZerProg studio
License-File: LICENSE
Requires-Dist: tqdm
